dask_sas_reader/__init__.py
dask_sas_reader/sas.py
tests/__init__.py
tests/test_sas.py
dask_sas_reader-0.1.0.dist-info/LICENSE
dask_sas_reader-0.1.0.dist-info/METADATA
dask_sas_reader-0.1.0.dist-info/WHEEL
dask_sas_reader-0.1.0.dist-info/top_level.txt
dask_sas_reader-0.1.0.dist-info/zip-safe
dask_sas_reader-0.1.0.dist-info/RECORD
