Metadata-Version: 2.1
Name: dask-sas-reader
Version: 0.1.0
Summary: Read SAS files into a Python Dask DataFrame.
Home-page: https://github.com/IMTorgOpenDataTools/dask-sas-reader
Author-email: information@mgmt-tech.org
License: MIT License
License-File: LICENSE
Requires-Dist: build
Requires-Dist: dask
Requires-Dist: pyreadstat
